Mariarandomizer/Mariarandomizer.py
Mariarandomizer/__init__.py
Mariarandomizer-0.1.0.dist-info/AUTHORS.rst
Mariarandomizer-0.1.0.dist-info/LICENSE
Mariarandomizer-0.1.0.dist-info/METADATA
Mariarandomizer-0.1.0.dist-info/WHEEL
Mariarandomizer-0.1.0.dist-info/top_level.txt
Mariarandomizer-0.1.0.dist-info/RECORD
